sologm/__init__.py
sologm/cli/__init__.py
sologm/cli/act.py
sologm/cli/dice.py
sologm/cli/event.py
sologm/cli/game.py
sologm/cli/main.py
sologm/cli/oracle.py
sologm/cli/scene.py
sologm/cli/rendering/__init__.py
sologm/cli/rendering/base.py
sologm/cli/rendering/markdown_renderer.py
sologm/cli/rendering/rich_renderer.py
sologm/cli/rendering/tests/__init__.py
sologm/cli/rendering/tests/conftest.py
sologm/cli/rendering/tests/test_markdown_renderer.py
sologm/cli/rendering/tests/test_rich_renderer.py
sologm/cli/utils/__init__.py
sologm/cli/utils/display.py
sologm/cli/utils/markdown.py
sologm/cli/utils/structured_editor.py
sologm/cli/utils/styled_text.py
sologm/cli/utils/tests/__init__.py
sologm/cli/utils/tests/conftest.py
sologm/cli/utils/tests/test_display.py
sologm/cli/utils/tests/test_markdown.py
sologm/cli/utils/tests/test_structured_editor.py
sologm/cli/utils/tests/test_styled_text.py
sologm/core/README.md
sologm/core/__init__.py
sologm/core/act.py
sologm/core/base_manager.py
sologm/core/dice.py
sologm/core/event.py
sologm/core/factory.py
sologm/core/game.py
sologm/core/oracle.py
sologm/core/scene.py
sologm/core/prompts/__init__.py
sologm/core/prompts/act.py
sologm/core/prompts/oracle.py
sologm/core/prompts/tests/__init__.py
sologm/core/prompts/tests/conftest.py
sologm/core/prompts/tests/test_act_prompts.py
sologm/core/prompts/tests/test_oracle_prompts.py
sologm/core/tests/conftest.py
sologm/core/tests/test_act.py
sologm/core/tests/test_base_manager.py
sologm/core/tests/test_dice.py
sologm/core/tests/test_event.py
sologm/core/tests/test_factory.py
sologm/core/tests/test_game.py
sologm/core/tests/test_oracle.py
sologm/core/tests/test_scene.py
sologm/core/tests/test_transaction_isolation.py
sologm/database/__init__.py
sologm/database/session.py
sologm/integrations/__init__.py
sologm/integrations/anthropic.py
sologm/integrations/tests/conftest.py
sologm/integrations/tests/test_anthropic.py
sologm/models/README.md
sologm/models/__init__.py
sologm/models/act.py
sologm-0.4.1.dist-info/METADATA
sologm-0.4.1.dist-info/WHEEL
sologm-0.4.1.dist-info/entry_points.txt
sologm-0.4.1.dist-info/licenses/LICENSE.md
sologm-0.4.1.dist-info/RECORD
