Metadata-Version: 2.4
Name: sologm
Version: 0.4.1
Summary: Solo RPG Helper command-line application with AI-enabled features
Project-URL: Homepage, https://github.com/phobologic/sologm
Project-URL: Issues, https://github.com/phobologic/sologm/issues
Author: Michael Barrett
License-Expression: MIT
License-File: LICENSE.md
Classifier: Development Status :: 4 - Beta
Classifier: Intended Audience :: End Users/Desktop
Classifier: License :: OSI Approved :: MIT License
Classifier: Programming Language :: Python :: 3
Classifier: Programming Language :: Python :: 3.13
Classifier: Topic :: Games/Entertainment :: Role-Playing
Requires-Python: >=3.13
Requires-Dist: anthropic>=0.5.0
Requires-Dist: pyyaml>=6.0
Requires-Dist: rich>=13.3.5
Requires-Dist: sqlalchemy>=2.0.40
Requires-Dist: typer>=0.9.0
Provides-Extra: dev
Requires-Dist: alembic>=1.15.2; extra == 'dev'
Requires-Dist: black>=23.3.0; extra == 'dev'
Requires-Dist: isort>=5.12.0; extra == 'dev'
Requires-Dist: mypy>=1.3.0; extra == 'dev'
Requires-Dist: pytest-cov>=4.1.0; extra == 'dev'
Requires-Dist: pytest>=7.3.1; extra == 'dev'
Requires-Dist: types-pyyaml>=6.0.12.20250402; extra == 'dev'
